posaydones_material_theming/__init__.py
posaydones_material_theming/__main__.py
posaydones_material_theming/data/__init__.py
posaydones_material_theming/data/pmt.cmb
posaydones_material_theming/data/pmt.ui
posaydones_material_theming/gui/__init__.py
posaydones_material_theming/gui/window.py
posaydones_material_theming/misc/__init__.py
posaydones_material_theming/misc/utils.py
posaydones_material_theming/modules/__init__.py
posaydones_material_theming/modules/templates.py
posaydones_material_theming/modules/theming.py
posaydones_material_theming/modules/wallpaper.py
posaydones_material_theming-0.2.4.dist-info/METADATA
posaydones_material_theming-0.2.4.dist-info/WHEEL
posaydones_material_theming-0.2.4.dist-info/entry_points.txt
posaydones_material_theming-0.2.4.dist-info/RECORD
