Metadata-Version: 2.1
Name: posaydones-material-theming
Version: 0.2.4
Summary: 
Author: posaydone
Author-email: poseaydone@ya.ru
Requires-Python: >=3.11,<4.0
Classifier: Programming Language :: Python :: 3
Classifier: Programming Language :: Python :: 3.11
Requires-Dist: chevron
Requires-Dist: colorthief
Requires-Dist: material-color-utilities-python
Requires-Dist: pygobject
Requires-Dist: toml
